{
    "items": [
        {
            "name": "Hybryda",
            "artists": [
                "Sok\u00f3\u0142",
                "Wowo"
            ]
        },
        {
            "name": "Lepiej jak jest lepiej",
            "artists": [
                "Sok\u00f3\u0142",
                "Mateusz Krautwurst"
            ]
        },
        {
            "name": "Pluszowy",
            "artists": [
                "Sok\u00f3\u0142"
            ]
        },
        {
            "name": "Pomy\u0142ka",
            "artists": [
                "Sok\u00f3\u0142",
                "Andrzej Zaucha"
            ]
        },
        {
            "name": "Sprytny Eskimos",
            "artists": [
                "Sok\u00f3\u0142",
                "Igo"
            ]
        },
        {
            "name": "I tak i nie",
            "artists": [
                "Sok\u00f3\u0142",
                "Hewra"
            ]
        },
        {
            "name": "Za r\u0119ce",
            "artists": [
                "Sok\u00f3\u0142"
            ]
        },
        {
            "name": "Nie da na da",
            "artists": [
                "Sok\u00f3\u0142",
                "Marcin Pyszora"
            ]
        },
        {
            "name": "Napad na bankiet",
            "artists": [
                "Sok\u00f3\u0142",
                "PRO8L3M",
                "Steez83",
                "Taco Hemingway"
            ]
        },
        {
            "name": "Z Tob\u0105",
            "artists": [
                "Sok\u00f3\u0142"
            ]
        },
        {
            "name": "Ska\u017cony",
            "artists": [
                "Sok\u00f3\u0142"
            ]
        },
        {
            "name": "MC Hasselblad",
            "artists": [
                "Sok\u00f3\u0142"
            ]
        },
        {
            "name": "Koniec gatunku",
            "artists": [
                "Sok\u00f3\u0142",
                "Wowo",
                "Lena Osi\u0144ska"
            ]
        },
        {
            "name": "Chcemy by\u0107 wy\u017cej",
            "artists": [
                "Sok\u00f3\u0142"
            ]
        }
    ]
}